{"frameRate":12,"armature":[{"skin":[{"name":"","slot":[{"display":[{"path":"heart","type":"image","name":"heart","transform":{}},{"path":"question","type":"image","name":"question","transform":{"y":-32.445142,"x":130.568457}}],"name":"heart"},{"display":[{"path":"eatting-0","type":"image","name":"eatting-0","transform":{"y":-83.95}},{"path":"eatting-6","type":"image","name":"eatting-6","transform":{"y":-83.95}},{"path":"eatting-5","type":"image","name":"eatting-5","transform":{"y":-83.95}},{"path":"eatting-4","type":"image","name":"eatting-4","transform":{"y":-83.95}},{"path":"eatting-3","type":"image","name":"eatting-3","transform":{"y":-83.95}},{"path":"eatting-2","type":"image","name":"eatting-2","transform":{"y":-83.95}},{"path":"eatting-1","type":"image","name":"eatting-1","transform":{"y":-83.95}},{"path":"eatting-10","type":"image","name":"eatting-10","transform":{"y":-83.95}},{"path":"eatting-9","type":"image","name":"eatting-9","transform":{"y":-83.95}},{"path":"eatting-8","type":"image","name":"eatting-8","transform":{"y":-83.95}},{"path":"eatting-7","type":"image","name":"eatting-7","transform":{"y":-83.95}},{"path":"send-heart-09","type":"image","name":"send-heart-09","transform":{"y":-80.3}},{"path":"send-heart-08","type":"image","name":"send-heart-08","transform":{"y":-80.3}},{"path":"send-heart-07","type":"image","name":"send-heart-07","transform":{"y":-80.3}},{"path":"send-heart-06","type":"image","name":"send-heart-06","transform":{"y":-80.3}},{"path":"send-heart-05","type":"image","name":"send-heart-05","transform":{"y":-80.3}},{"path":"send-heart-04","type":"image","name":"send-heart-04","transform":{"y":-80.3}},{"path":"send-heart-03","type":"image","name":"send-heart-03","transform":{"y":-80.3}},{"path":"send-heart-02","type":"image","name":"send-heart-02","transform":{"y":-80.3}},{"path":"send-heart-01","type":"image","name":"send-heart-01","transform":{"y":-80.3}},{"path":"send-heart-00","type":"image","name":"send-heart-00","transform":{"y":-80.3}},{"path":"dance-6","type":"image","name":"dance-6","transform":{"y":-102.2}},{"path":"dance-5","type":"image","name":"dance-5","transform":{"y":-102.2}},{"path":"dance-4","type":"image","name":"dance-4","transform":{"y":-102.2}},{"path":"dance-3","type":"image","name":"dance-3","transform":{"y":-102.2}},{"path":"dance-2","type":"image","name":"dance-2","transform":{"y":-102.2}},{"path":"dance-1","type":"image","name":"dance-1","transform":{"y":-102.2}},{"path":"dance-0","type":"image","name":"dance-0","transform":{"y":-102.2}},{"path":"quest-5","type":"image","name":"quest-5","transform":{"y":-86.87}},{"path":"quest-4","type":"image","name":"quest-4","transform":{"y":-87.6}},{"path":"quest-3","type":"image","name":"quest-3","transform":{"y":-87.6}},{"path":"quest-2","type":"image","name":"quest-2","transform":{"y":-87.6}},{"path":"quest-1","type":"image","name":"quest-1","transform":{"y":-87.6}},{"path":"quest-0","type":"image","name":"quest-0","transform":{"y":-87.6}},{"path":"laugh-15","type":"image","name":"laugh-15","transform":{"y":-87.6}},{"path":"laugh-14","type":"image","name":"laugh-14","transform":{"y":-87.6}},{"path":"laugh-11","type":"image","name":"laugh-11","transform":{"y":-87.6}},{"path":"laugh-10","type":"image","name":"laugh-10","transform":{"y":-87.6}},{"path":"laugh-09","type":"image","name":"laugh-09","transform":{"y":-87.6}},{"path":"laugh-08","type":"image","name":"laugh-08","transform":{"y":-87.6}},{"path":"laugh-05","type":"image","name":"laugh-05","transform":{"y":-87.6}},{"path":"laugh-04","type":"image","name":"laugh-04","transform":{"y":-87.6}},{"path":"laugh-03","type":"image","name":"laugh-03","transform":{"y":-87.6}},{"path":"laugh-02","type":"image","name":"laugh-02","transform":{"y":-87.6}},{"path":"laugh-01","type":"image","name":"laugh-01","transform":{"y":-87.6}},{"path":"laugh-00","type":"image","name":"laugh-00","transform":{"y":-87.6}}],"name":"images"}]}],"type":"Armature","frameRate":12,"animation":[{"playTimes":0,"frame":[],"duration":160,"ik":[],"slot":[{"frame":[{"duration":3,"tweenEasing":null},{"duration":1,"displayIndex":5,"tweenEasing":null},{"duration":1,"displayIndex":4,"tweenEasing":null},{"duration":1,"displayIndex":3,"tweenEasing":null},{"duration":1,"displayIndex":2,"tweenEasing":null},{"duration":1,"displayIndex":10,"tweenEasing":null},{"duration":1,"displayIndex":9,"tweenEasing":null},{"duration":1,"displayIndex":8,"tweenEasing":null},{"duration":1,"displayIndex":7,"tweenEasing":null},{"duration":1,"displayIndex":10,"tweenEasing":null},{"duration":1,"displayIndex":9,"tweenEasing":null},{"duration":1,"displayIndex":8,"tweenEasing":null},{"duration":1,"displayIndex":7,"tweenEasing":null},{"duration":1,"displayIndex":10,"tweenEasing":null},{"duration":1,"displayIndex":9,"tweenEasing":null},{"duration":1,"displayIndex":8,"tweenEasing":null},{"duration":1,"displayIndex":7,"tweenEasing":null},{"duration":5,"displayIndex":10,"tweenEasing":null},{"duration":1,"displayIndex":9,"tweenEasing":null},{"duration":1,"displayIndex":8,"tweenEasing":null},{"duration":1,"displayIndex":7,"tweenEasing":null},{"duration":6,"displayIndex":10,"tweenEasing":null},{"duration":1,"displayIndex":1,"tweenEasing":null},{"duration":1,"displayIndex":2,"tweenEasing":null},{"duration":1,"displayIndex":3,"tweenEasing":null},{"duration":1,"displayIndex":4,"tweenEasing":null},{"duration":1,"displayIndex":6,"tweenEasing":null},{"duration":122,"tweenEasing":null},{"duration":0,"tweenEasing":null}],"name":"images"}],"bone":[{"frame":[{"duration":160,"transform":{}}],"name":"root"},{"frame":[{"duration":160,"transform":{}}],"name":"heart-scale"},{"frame":[{"duration":160,"transform":{}}],"name":"heart-rotation"}],"name":"st-0","ffd":[]},{"playTimes":0,"frame":[],"duration":108,"ik":[],"slot":[{"frame":[{"duration":9,"displayIndex":-1,"tweenEasing":null},{"duration":18,"tweenEasing":null},{"duration":10,"tweenEasing":0},{"duration":71,"displayIndex":-1,"tweenEasing":null,"color":{"aM":0}}],"name":"heart"},{"frame":[{"duration":2,"displayIndex":20,"tweenEasing":null},{"duration":1,"displayIndex":19,"tweenEasing":null},{"duration":1,"displayIndex":18,"tweenEasing":null},{"duration":1,"displayIndex":17,"tweenEasing":null},{"duration":1,"displayIndex":16,"tweenEasing":null},{"duration":1,"displayIndex":15,"tweenEasing":null},{"duration":1,"displayIndex":14,"tweenEasing":null},{"duration":1,"displayIndex":13,"tweenEasing":null},{"duration":2,"displayIndex":12,"tweenEasing":null},{"duration":45,"displayIndex":11,"tweenEasing":null},{"duration":1,"displayIndex":12,"tweenEasing":null},{"duration":1,"displayIndex":13,"tweenEasing":null},{"duration":1,"displayIndex":14,"tweenEasing":null},{"duration":1,"displayIndex":15,"tweenEasing":null},{"duration":1,"displayIndex":17,"tweenEasing":null},{"duration":1,"displayIndex":18,"tweenEasing":null},{"duration":1,"displayIndex":19,"tweenEasing":null},{"duration":45,"displayIndex":20,"tweenEasing":null},{"duration":0,"displayIndex":20,"tweenEasing":null}],"name":"images"}],"bone":[{"frame":[{"duration":108,"transform":{}}],"name":"root"},{"frame":[{"duration":9,"transform":{}},{"duration":1,"tweenEasing":0,"transform":{"scX":1.5,"scY":1.5}},{"duration":1,"tweenEasing":0,"transform":{"scX":0.5,"scY":0.5}},{"duration":2,"tweenEasing":0,"transform":{}},{"duration":14,"curve":[0,0,0.5,1],"transform":{"scX":1.2777,"scY":1.21}},{"duration":10,"tweenEasing":0,"transform":{"scX":1.2,"scY":1.2}},{"duration":71,"transform":{"scX":2,"scY":2}}],"name":"heart-scale"},{"frame":[{"duration":14,"transform":{}},{"duration":23,"curve":[0.5,0,0.5,1],"transform":{}},{"duration":71,"transform":{"skY":35,"y":-29.882476999999998,"skX":35,"x":-16.259581999999998}}],"name":"heart-rotation"}],"name":"st-1","ffd":[]},{"playTimes":0,"frame":[{"duration":6,"tweenEasing":null},{"duration":0,"tweenEasing":null,"events":[{"name":"loops","ints":[5]}]}],"duration":6,"ik":[],"slot":[{"frame":[{"duration":1,"displayIndex":27,"tweenEasing":null},{"duration":1,"displayIndex":26,"tweenEasing":null},{"duration":1,"displayIndex":25,"tweenEasing":null},{"duration":1,"displayIndex":24,"tweenEasing":null},{"duration":1,"displayIndex":23,"tweenEasing":null},{"duration":1,"displayIndex":22,"tweenEasing":null},{"duration":0,"displayIndex":21,"tweenEasing":null}],"name":"images"}],"bone":[{"frame":[{"duration":6,"transform":{}}],"name":"root"},{"frame":[{"duration":6,"transform":{}}],"name":"heart-rotation"},{"frame":[{"duration":6,"transform":{}}],"name":"heart-scale"}],"name":"st-2","ffd":[]},{"playTimes":0,"frame":[],"duration":60,"ik":[],"slot":[{"frame":[{"duration":12,"displayIndex":-1,"tweenEasing":null},{"duration":3,"displayIndex":1,"tweenEasing":0,"color":{"aM":0}},{"duration":9,"displayIndex":1,"tweenEasing":0},{"duration":3,"displayIndex":1,"tweenEasing":0},{"duration":33,"displayIndex":1,"tweenEasing":null,"color":{"aM":0}}],"name":"heart"},{"frame":[{"duration":2,"displayIndex":28,"tweenEasing":null},{"duration":1,"displayIndex":28,"tweenEasing":null},{"duration":1,"displayIndex":30,"tweenEasing":null},{"duration":1,"displayIndex":33,"tweenEasing":null},{"duration":1,"displayIndex":32,"tweenEasing":null},{"duration":1,"displayIndex":31,"tweenEasing":null},{"duration":1,"displayIndex":30,"tweenEasing":null},{"duration":1,"displayIndex":29,"tweenEasing":null},{"duration":51,"displayIndex":28,"tweenEasing":null},{"duration":0,"displayIndex":28,"tweenEasing":null}],"name":"images"}],"bone":[{"frame":[{"duration":60,"transform":{}}],"name":"root"},{"frame":[{"duration":12,"transform":{}},{"duration":15,"curve":[0.5,0,0.5,1],"transform":{}},{"duration":33,"transform":{"y":-12.051058999999999,"scX":1.15,"scY":1.15,"x":6.489042999999999}}],"name":"heart-rotation"},{"frame":[{"duration":60,"transform":{}}],"name":"heart-scale"}],"name":"st-3","ffd":[]},{"playTimes":0,"frame":[],"duration":65,"ik":[],"slot":[{"frame":[{"duration":2,"displayIndex":45,"tweenEasing":null},{"duration":1,"displayIndex":44,"tweenEasing":null},{"duration":1,"displayIndex":43,"tweenEasing":null},{"duration":1,"displayIndex":42,"tweenEasing":null},{"duration":1,"displayIndex":41,"tweenEasing":null},{"duration":6,"displayIndex":40,"tweenEasing":null},{"duration":1,"displayIndex":39,"tweenEasing":null},{"duration":1,"displayIndex":38,"tweenEasing":null},{"duration":1,"displayIndex":37,"tweenEasing":null},{"duration":2,"displayIndex":36,"tweenEasing":null},{"duration":1,"displayIndex":35,"tweenEasing":null},{"duration":1,"displayIndex":34,"tweenEasing":null},{"duration":1,"displayIndex":36,"tweenEasing":null},{"duration":1,"displayIndex":35,"tweenEasing":null},{"duration":1,"displayIndex":34,"tweenEasing":null},{"duration":1,"displayIndex":36,"tweenEasing":null},{"duration":1,"displayIndex":35,"tweenEasing":null},{"duration":1,"displayIndex":34,"tweenEasing":null},{"duration":10,"displayIndex":36,"tweenEasing":null},{"duration":1,"displayIndex":35,"tweenEasing":null},{"duration":1,"displayIndex":37,"tweenEasing":null},{"duration":1,"displayIndex":39,"tweenEasing":null},{"duration":1,"displayIndex":41,"tweenEasing":null},{"duration":1,"displayIndex":43,"tweenEasing":null},{"duration":25,"displayIndex":45,"tweenEasing":null},{"duration":0,"displayIndex":45,"tweenEasing":null}],"name":"images"}],"bone":[{"frame":[{"duration":65,"transform":{}}],"name":"root"},{"frame":[{"duration":65,"transform":{}}],"name":"heart-rotation"},{"frame":[{"duration":65,"transform":{}}],"name":"heart-scale"}],"name":"st-4","ffd":[]}],"aabb":{"width":210.24,"y":-191.99,"height":210.24,"x":-105.12},"ik":[],"slot":[{"displayIndex":28,"name":"images","parent":"root","color":{}},{"z":1,"displayIndex":-1,"name":"heart","parent":"heart-scale","color":{}}],"bone":[{"name":"root","transform":{}},{"transform":{"y":-80.3},"name":"heart-rotation","parent":"root"},{"transform":{"y":-18.215106000000002,"x":-80.3},"name":"heart-scale","parent":"heart-rotation"}],"name":"emote","defaultActions":[{"gotoAndPlay":"st-0"}]}],"isGlobal":0,"name":"emotes","version":"5.0"}